xhs_bailian_mcp_server/__init__.py
xhs_bailian_mcp_server/server.py
xuanxi_621_xhs_bailian_mcp_server-0.1.0.dist-info/METADATA
xuanxi_621_xhs_bailian_mcp_server-0.1.0.dist-info/WHEEL
xuanxi_621_xhs_bailian_mcp_server-0.1.0.dist-info/entry_points.txt
xuanxi_621_xhs_bailian_mcp_server-0.1.0.dist-info/RECORD
